pyansysv23/__init__.py
pyansysv23/analysis.py
pyansysv23/annotation.py
pyansysv23/core.py
pyansysv23/document.py
pyansysv23/extensibility.py
pyansysv23/geometry.py
pyansysv23/instance.py
pyansysv23/modeler.py
pyansysv23-0.23.0.dist-info/licenses/LICENSE
pyansysv23-0.23.0.dist-info/METADATA
pyansysv23-0.23.0.dist-info/WHEEL
pyansysv23-0.23.0.dist-info/top_level.txt
pyansysv23-0.23.0.dist-info/RECORD
