Metadata-Version: 2.4
Name: PyAnsysV23
Version: 0.23.0
Summary: Virtual SpaceClaim API V23 library for Python
Home-page: https://github.com/pyansys/pyansysv23
Author: PyAnsys Contributors
Author-email: PyAnsys Contributors <contact@pyansys.dev>
License: MIT
Project-URL: Homepage, https://github.com/pyansys/pyansysv23
Project-URL: Documentation, https://github.com/pyansys/pyansysv23/blob/main/README.md
Project-URL: Repository, https://github.com/pyansys/pyansysv23.git
Project-URL: Bug Tracker, https://github.com/pyansys/pyansysv23/issues
Project-URL: Changelog, https://github.com/pyansys/pyansysv23/releases
Keywords: ansys,spaceclaim,cad,api,modeling,geometry,3d,mechanical,simulation
Classifier: Development Status :: 3 - Alpha
Classifier: Environment :: Console
Classifier: Intended Audience :: Developers
Classifier: Intended Audience :: Science/Research
Classifier: Intended Audience :: Manufacturing
Classifier: License :: OSI Approved :: MIT License
Classifier: Operating System :: Microsoft :: Windows
Classifier: Programming Language :: Python :: 3
Classifier: Programming Language :: Python :: 3.7
Classifier: Programming Language :: Python :: 3.8
Classifier: Programming Language :: Python :: 3.9
Classifier: Programming Language :: Python :: 3.10
Classifier: Programming Language :: Python :: 3.11
Classifier: Programming Language :: Python :: 3.12
Classifier: Topic :: Scientific/Engineering
Classifier: Topic :: Software Development :: Libraries :: Python Modules
Requires-Python: >=3.7
License-File: LICENSE
Provides-Extra: dev
Requires-Dist: pytest>=6.0; extra == "dev"
Requires-Dist: pytest-cov>=2.10; extra == "dev"
Requires-Dist: black>=21.0; extra == "dev"
Requires-Dist: flake8>=3.9; extra == "dev"
Requires-Dist: mypy>=0.910; extra == "dev"
Requires-Dist: setuptools>=45; extra == "dev"
Requires-Dist: wheel; extra == "dev"
Requires-Dist: build; extra == "dev"
Requires-Dist: twine>=3.0; extra == "dev"
Provides-Extra: docs
Requires-Dist: sphinx>=4.0; extra == "docs"
Requires-Dist: sphinx-rtd-theme>=1.0; extra == "docs"
Dynamic: author
Dynamic: license-file
Dynamic: requires-python
